dicetables/__init__.py
dicetables/additiveevents.py
dicetables/dicepool.py
dicetables/dicepool_collection.py
dicetables/dicerecord.py
dicetables/dicetable.py
dicetables/dieevents.py
dicetables/eventsinfo.py
dicetables/parser.py
dicetables/roller.py
dicetables/eventsbases/__init__.py
dicetables/eventsbases/eventerrors.py
dicetables/eventsbases/integerevents.py
dicetables/eventsbases/protodie.py
dicetables/factory/__init__.py
dicetables/factory/errorhandler.py
dicetables/factory/eventsfactory.py
dicetables/factory/factorytools.py
dicetables/factory/warninghandler.py
dicetables/tools/__init__.py
dicetables/tools/alias_table.py
dicetables/tools/dictcombiner.py
dicetables/tools/indexedvalues.py
dicetables/tools/limit_checker.py
dicetables/tools/listtostring.py
dicetables/tools/numberforamtter.py
dicetables/tools/orderedcombinations.py
dicetables-4.0.3.dist-info/METADATA
dicetables-4.0.3.dist-info/WHEEL
dicetables-4.0.3.dist-info/licenses/LICENSE
dicetables-4.0.3.dist-info/RECORD
