Metadata-Version: 2.4
Name: dicetables
Version: 4.0.3
Summary: get all combinations for any set of dice
Project-URL: Homepage, https://allthedice.com
Project-URL: Documentation, https://dice-tables.readthedocs.io/en/latest
Project-URL: Repository, https://github.com/eric-s-s/dice-tables.git
Project-URL: Issues, https://github.com/eric-s-s/dice-tables/issues
Project-URL: Changelog, https://github.com/eric-s-s/dice-tables/blob/master/CHANGELOG.md
Author-email: Eric Shaw <shaweric01@gmail.com>
Maintainer-email: Eric Shaw <shaweric01@gmail.com>
License: MIT License
License-File: LICENSE
Classifier: Development Status :: 5 - Production/Stable
Classifier: Intended Audience :: Developers
Classifier: License :: OSI Approved :: MIT License
Classifier: Operating System :: OS Independent
Classifier: Programming Language :: Python
Classifier: Programming Language :: Python :: 3
Classifier: Topic :: Games/Entertainment :: Role-Playing
Classifier: Topic :: Scientific/Engineering :: Mathematics
Requires-Python: >=3.7
